embree.libs/libembree4-ebd25b5b.so.4
embree.libs/libtbb-bd3ebe0a.so.12.9
embree-4.1.0.dist-info/RECORD
embree-4.1.0.dist-info/WHEEL
embree-4.1.0.dist-info/LICENSE.txt
embree-4.1.0.dist-info/top_level.txt
embree-4.1.0.dist-info/METADATA
embree/wrapper.cpython-36m-x86_64-linux-gnu.so
