Metadata-Version: 2.1
Name: embree
Version: 4.1.0
Summary: Ray queries on triangular meshes.
Home-page: UNKNOWN
License: UNKNOWN
Platform: UNKNOWN
License-File: LICENSE.txt
Requires-Dist: numpy
